markdown_version_annotations/__init__.py
markdown_version_annotations-1.0.1.dist-info/LICENSE.txt
markdown_version_annotations-1.0.1.dist-info/METADATA
markdown_version_annotations-1.0.1.dist-info/WHEEL
markdown_version_annotations-1.0.1.dist-info/RECORD
