Metadata-Version: 2.1
Name: markdown-version-annotations
Version: 1.0.1
Summary: Markdown plugin to add custom admonitions for documenting version differences
Home-page: https://github.com/glennmatthews/markdown-version-annotations
License: MIT
Keywords: markdown
Author: Glenn Matthews
Author-email: glenn@e-dad.net
Requires-Python: >=3.7,<4.0
Classifier: Development Status :: 5 - Production/Stable
Classifier: Intended Audience :: Developers
Classifier: License :: OSI Approved :: MIT License
Classifier: Programming Language :: Python :: 3
Classifier: Programming Language :: Python :: 3.7
Classifier: Programming Language :: Python :: 3.8
Classifier: Programming Language :: Python :: 3.9
Classifier: Programming Language :: Python :: 3.10
Classifier: Programming Language :: Python :: 3.11
Classifier: Programming Language :: Python :: 3.12
Requires-Dist: markdown (>=3.3.7,<4.0.0)
Project-URL: Repository, https://github.com/glennmatthews/markdown-version-annotations
